isr_matcher/__init__.py
isr_matcher/_constants/__init__.py
isr_matcher/_constants/_filters.py
isr_matcher/_constants/_km_directions.py
isr_matcher/_constants/_parse.py
isr_matcher/_constants/_properties.py
isr_matcher/_constants/logging.py
isr_matcher/_constants/tracks_kms.json
isr_matcher/_constants/tracks_lengths.json
isr_matcher/data_handlers/__init__.py
isr_matcher/data_handlers/gnss_data_import.py
isr_matcher/data_handlers/import_functions.py
isr_matcher/data_handlers/rail_data_import.py
isr_matcher/data_handlers/transformer.py
isr_matcher/geometry/__init__.py
isr_matcher/geometry/gnss_series.py
isr_matcher/geometry/kilometrage.py
isr_matcher/geometry/map.py
isr_matcher/geometry/operational_point.py
isr_matcher/geometry/rail.py
isr_matcher/geometry/track_segment.py
isr_matcher/map_matching/__init__.py
isr_matcher/map_matching/hmm.py
isr_matcher/map_matching/isr_matcher.py
isr_matcher/ops/__init__.py
isr_matcher/ops/_functions.py
isr_matcher/ops/_postprocessing.py
isr_matcher/ops/_preprocessing.py
isr_matcher/ops/functions.py
isr_matcher-0.0.7.dist-info/LICENSE
isr_matcher-0.0.7.dist-info/METADATA
isr_matcher-0.0.7.dist-info/WHEEL
isr_matcher-0.0.7.dist-info/top_level.txt
isr_matcher-0.0.7.dist-info/RECORD
