Metadata-Version: 2.1
Name: isr_matcher
Version: 0.0.7
Summary: A package for map matching to german rail network
Author-email: Marco Gillwald <marco.gillwald@gmx.de>
License: Copyright 2024 Marco Gillwald
Project-URL: Homepage, https://github.com/mgillwald/isr_matcher
Project-URL: Issues, https://github.com/mgillwald/isr_matcher/issues
Keywords: map matching,rail,ISR
Classifier: Programming Language :: Python :: 3
Classifier: License :: OSI Approved :: Apache Software License
Classifier: Operating System :: OS Independent
Requires-Python: >=3.11
License-File: LICENSE
Requires-Dist: folium >=0.15.1
Requires-Dist: matplotlib >=3.8.2
Requires-Dist: numpy >=1.26.4
Requires-Dist: pandas >=2.2.1
Requires-Dist: pyproj >=3.6.0
Requires-Dist: pytest >=7.4.3
Requires-Dist: requests >=2.31.0
Requires-Dist: scipy >=1.12.0
Requires-Dist: shapely >=2.0.3
